replus/__init__.py
replus/exceptions.py
replus-0.3.0.dist-info/LICENSE
replus-0.3.0.dist-info/METADATA
replus-0.3.0.dist-info/WHEEL
replus-0.3.0.dist-info/RECORD
