Metadata-Version: 2.1
Name: replus
Version: 0.3.0
Summary: A library for managing regula expressions with templates
License: MIT
Author: Biagio Distefano
Author-email: biagiodistefano92@gmail.com
Requires-Python: >=3.11,<4.0
Classifier: License :: OSI Approved :: MIT License
Classifier: Programming Language :: Python :: 3
Classifier: Programming Language :: Python :: 3.11
Requires-Dist: coverage (>=7.3.0,<8.0.0)
Requires-Dist: pytest-cov (>=4.1.0,<5.0.0)
Requires-Dist: regex (>=2023.8.8,<2024.0.0)
